odoo/addons/purchase_report_shipping_address/README.rst
odoo/addons/purchase_report_shipping_address/__init__.py
odoo/addons/purchase_report_shipping_address/__manifest__.py
odoo/addons/purchase_report_shipping_address/i18n/it.po
odoo/addons/purchase_report_shipping_address/i18n/purchase_report_shipping_address.pot
odoo/addons/purchase_report_shipping_address/models/__init__.py
odoo/addons/purchase_report_shipping_address/models/stock_warehouse.py
odoo/addons/purchase_report_shipping_address/readme/CONFIGURE.md
odoo/addons/purchase_report_shipping_address/readme/CONTRIBUTORS.md
odoo/addons/purchase_report_shipping_address/readme/DESCRIPTION.md
odoo/addons/purchase_report_shipping_address/reports/purchase_order_templates.xml
odoo/addons/purchase_report_shipping_address/reports/purchase_quotation_templates.xml
odoo/addons/purchase_report_shipping_address/static/description/icon.png
odoo/addons/purchase_report_shipping_address/static/description/index.html
odoo/addons/purchase_report_shipping_address/views/stock_warehouse_views.xml
odoo_addon_purchase_report_shipping_address-18.0.1.0.0.2.dist-info/METADATA
odoo_addon_purchase_report_shipping_address-18.0.1.0.0.2.dist-info/WHEEL
odoo_addon_purchase_report_shipping_address-18.0.1.0.0.2.dist-info/top_level.txt
odoo_addon_purchase_report_shipping_address-18.0.1.0.0.2.dist-info/RECORD
